anykernel/__init__.py
anykernel/client.py
anykernel/exceptions.py
anykernel/hardware.py
anykernel/session.py
anykernel/backend/__init__.py
anykernel/backend/base.py
anykernel/backend/llama_cpp.py
anykernel/backend/loader.py
anykernel/backend/mlx_backend.py
anykernel/backend/registry.py
anykernel/backend/selector.py
anykernel/backend/vllm_backend.py
anykernel/model/__init__.py
anykernel/model/runner.py
anykernel/utils/__init__.py
anykernel/utils/cache.py
anykernel/utils/logger.py
anykernel-0.1.0.dist-info/METADATA
anykernel-0.1.0.dist-info/WHEEL
anykernel-0.1.0.dist-info/top_level.txt
anykernel-0.1.0.dist-info/RECORD
