Metadata-Version: 2.4
Name: anykernel
Version: 0.1.0
Summary: Zero-config inference OS for local LLMs - supports MLX, vLLM, and llama.cpp
Author: AnyKernel Team
License: MIT
Project-URL: Homepage, https://github.com/anykernel/anykernel
Project-URL: Documentation, https://github.com/anykernel/anykernel#readme
Project-URL: Repository, https://github.com/anykernel/anykernel
Keywords: llm,inference,llama,mlx,vllm,ai,machine-learning
Classifier: Development Status :: 3 - Alpha
Classifier: Intended Audience :: Developers
Classifier: License :: OSI Approved :: MIT License
Classifier: Programming Language :: Python :: 3
Classifier: Programming Language :: Python :: 3.9
Classifier: Programming Language :: Python :: 3.10
Classifier: Programming Language :: Python :: 3.11
Classifier: Programming Language :: Python :: 3.12
Classifier: Topic :: Scientific/Engineering :: Artificial Intelligence
Requires-Python: >=3.9
Requires-Dist: huggingface-hub>=0.20.0
Provides-Extra: llama
Requires-Dist: llama-cpp-python>=0.2.0; extra == "llama"
Provides-Extra: mlx
Requires-Dist: mlx>=0.4.0; extra == "mlx"
Requires-Dist: mlx-lm>=0.4.0; extra == "mlx"
Provides-Extra: vllm
Requires-Dist: vllm>=0.4.0; extra == "vllm"
Provides-Extra: cpu
Requires-Dist: llama-cpp-python>=0.2.0; extra == "cpu"
Provides-Extra: apple
Requires-Dist: mlx>=0.4.0; extra == "apple"
Requires-Dist: mlx-lm>=0.4.0; extra == "apple"
Provides-Extra: nvidia
Requires-Dist: vllm>=0.4.0; extra == "nvidia"
Provides-Extra: all
Requires-Dist: llama-cpp-python>=0.2.0; extra == "all"
Requires-Dist: mlx>=0.4.0; extra == "all"
Requires-Dist: mlx-lm>=0.4.0; extra == "all"
Requires-Dist: vllm>=0.4.0; extra == "all"
Provides-Extra: dev
Requires-Dist: pytest>=7.0; extra == "dev"
Requires-Dist: pytest-cov>=4.0; extra == "dev"
Requires-Dist: black>=23.0; extra == "dev"
Requires-Dist: ruff>=0.1.0; extra == "dev"
Requires-Dist: mypy>=1.0; extra == "dev"
